odoo/addons/web_ir_actions_act_window_message/README.rst
odoo/addons/web_ir_actions_act_window_message/__init__.py
odoo/addons/web_ir_actions_act_window_message/__manifest__.py
odoo/addons/web_ir_actions_act_window_message/i18n/ar.po
odoo/addons/web_ir_actions_act_window_message/i18n/de.po
odoo/addons/web_ir_actions_act_window_message/i18n/es.po
odoo/addons/web_ir_actions_act_window_message/i18n/eu.po
odoo/addons/web_ir_actions_act_window_message/i18n/fi.po
odoo/addons/web_ir_actions_act_window_message/i18n/fr.po
odoo/addons/web_ir_actions_act_window_message/i18n/hr.po
odoo/addons/web_ir_actions_act_window_message/i18n/it.po
odoo/addons/web_ir_actions_act_window_message/i18n/nl.po
odoo/addons/web_ir_actions_act_window_message/i18n/nl_NL.po
odoo/addons/web_ir_actions_act_window_message/i18n/pt.po
odoo/addons/web_ir_actions_act_window_message/i18n/pt_BR.po
odoo/addons/web_ir_actions_act_window_message/i18n/ro.po
odoo/addons/web_ir_actions_act_window_message/i18n/sl.po
odoo/addons/web_ir_actions_act_window_message/i18n/tr.po
odoo/addons/web_ir_actions_act_window_message/i18n/web_ir_actions_act_window_message.pot
odoo/addons/web_ir_actions_act_window_message/models/__init__.py
odoo/addons/web_ir_actions_act_window_message/models/ir_actions.py
odoo/addons/web_ir_actions_act_window_message/readme/CONTRIBUTORS.md
odoo/addons/web_ir_actions_act_window_message/readme/DESCRIPTION.md
odoo/addons/web_ir_actions_act_window_message/readme/ROADMAP.md
odoo/addons/web_ir_actions_act_window_message/readme/USAGE.md
odoo/addons/web_ir_actions_act_window_message/security/ir.model.access.csv
odoo/addons/web_ir_actions_act_window_message/static/description/icon.png
odoo/addons/web_ir_actions_act_window_message/static/description/index.html
odoo/addons/web_ir_actions_act_window_message/static/src/js/web_ir_actions_act_window_message.esm.js
odoo/addons/web_ir_actions_act_window_message/static/src/js/web_ir_actions_act_window_msg_component.esm.js
odoo_addon_web_ir_actions_act_window_message-18.0.1.0.1.dist-info/METADATA
odoo_addon_web_ir_actions_act_window_message-18.0.1.0.1.dist-info/WHEEL
odoo_addon_web_ir_actions_act_window_message-18.0.1.0.1.dist-info/top_level.txt
odoo_addon_web_ir_actions_act_window_message-18.0.1.0.1.dist-info/RECORD
